flask_codemirror/__init__.py
flask_codemirror/fields.py
flask_codemirror/widgets.py
flask_codemirror-1.3.dist-info/LICENSE
flask_codemirror-1.3.dist-info/METADATA
flask_codemirror-1.3.dist-info/WHEEL
flask_codemirror-1.3.dist-info/top_level.txt
flask_codemirror-1.3.dist-info/RECORD
