Metadata-Version: 2.1
Name: flask-codemirror
Version: 1.3
Summary: Use CodeMirror Javascript library with Flask-WTF
Home-page: https://github.com/j0ack/flask-codemirror
Author: TROUVERIE Joachim
Author-email: jtrouverie@joakode.fr
License: GPL
Platform: any
Classifier: Development Status :: 5 - Production/Stable
Classifier: License :: OSI Approved :: GNU General Public License v3 (GPLv3)
Classifier: Environment :: Web Environment
Classifier: Intended Audience :: Developers
Classifier: Operating System :: OS Independent
Classifier: Framework :: Flask
Classifier: Programming Language :: Python :: 3
Classifier: Topic :: Internet :: WWW/HTTP :: Dynamic Content
Classifier: Topic :: Software Development :: Libraries :: Python Modules
Classifier: Topic :: Utilities
License-File: LICENSE
Requires-Dist: Flask
Requires-Dist: WTForms
Requires-Dist: requests
